setup.py
ternary.py
ternary.egg-info/PKG-INFO
ternary.egg-info/SOURCES.txt
ternary.egg-info/dependency_links.txt
ternary.egg-info/top_level.txt