Metadata-Version: 1.0
Name: ternary
Version: 0.1
Summary: Ternary operation implementation.
Home-page: UNKNOWN
Author: Wijnand Modderman
Author-email: maze@pyth0n.org
License: MIT
Keywords: ternary operation
Platform: UNKNOWN
